README.md
setup.py
configboy/__init__.py
configboy/build_config.py
configboy/config.py
configboy/config_1.py
configboy/configboy.py
configboy/run.py
configboy.egg-info/PKG-INFO
configboy.egg-info/SOURCES.txt
configboy.egg-info/dependency_links.txt
configboy.egg-info/entry_points.txt
configboy.egg-info/requires.txt
configboy.egg-info/top_level.txt