Metadata-Version: 1.0
Name: configboy
Version: 0.1.7
Summary: config library
Home-page: http://test.com
Author: aaronhua
Author-email: cjhdwyyx@163.com
License: UNKNOWN
Platform: all
